pytailwindcss_extra/__init__.py
pytailwindcss_extra/__main__.py
pytailwindcss_extra/logger.py
pytailwindcss_extra/main.py
pytailwindcss_extra-0.2.1.dist-info/METADATA
pytailwindcss_extra-0.2.1.dist-info/WHEEL
pytailwindcss_extra-0.2.1.dist-info/entry_points.txt
pytailwindcss_extra-0.2.1.dist-info/licenses/LICENSE.txt
pytailwindcss_extra-0.2.1.dist-info/RECORD
