Metadata-Version: 2.3
Name: pytailwindcss-extra
Version: 0.2.1
Summary: Use Tailwind CSS with daisyUI without Node.js and install it via pip.
Project-URL: Homepage, https://github.com/2mal3/pytailwindcss-extra
Project-URL: Repository, https://github.com/2mal3/pytailwindcss-extra
Project-URL: Issues, https://github.com/2mal3/pytailwindcss-extra/issues
Author-email: 2mal3 <56305732+2mal3@users.noreply.github.com>
License: LGPL-3.0
Keywords: cli,css,daisyui,tailwind
Classifier: Development Status :: 4 - Beta
Classifier: Intended Audience :: Developers
Classifier: License :: OSI Approved :: GNU Lesser General Public License v3 (LGPLv3)
Classifier: Operating System :: OS Independent
Classifier: Programming Language :: Python :: 3.8
Classifier: Programming Language :: Python :: 3.9
Classifier: Programming Language :: Python :: 3.10
Classifier: Programming Language :: Python :: 3.11
Classifier: Programming Language :: Python :: 3.12
Classifier: Programming Language :: Python :: 3.13
Classifier: Topic :: Software Development :: Libraries
Classifier: Topic :: Utilities
Requires-Python: >=3.8
Requires-Dist: niquests==3.*
Requires-Dist: platformdirs==4.*
Requires-Dist: tqdm==4.*
